resource_getters/__init__.py
resource_getters/config.py
resource_getters/getters.py
resource_getters/py.typed
resource_getters-1.0.0.dist-info/METADATA
resource_getters-1.0.0.dist-info/WHEEL
resource_getters-1.0.0.dist-info/licenses/LICENSE
resource_getters-1.0.0.dist-info/RECORD
