Metadata-Version: 2.4
Name: resource-getters
Version: 1.0.0
Summary: A minimal utility package for accessing application resources (icons, images, translations) in a clean and reusable way.
Author-email: Rafal Padkowski <rafaelp@poczta.onet.pl>
License-Expression: MIT
License-File: LICENSE
Requires-Python: >=3.13
